setup.py
djangocms_seotools/__init__.py
djangocms_seotools/admin.py
djangocms_seotools/cms_toolbar.py
djangocms_seotools/models.py
djangocms_seotools.egg-info/PKG-INFO
djangocms_seotools.egg-info/SOURCES.txt
djangocms_seotools.egg-info/dependency_links.txt
djangocms_seotools.egg-info/top_level.txt
djangocms_seotools/tests/__init__.py
djangocms_seotools/tests/test_title_extensions.py
djangocms_seotools/tests/urls.py