Metadata-Version: 1.0
Name: djangocms-seotools
Version: 1.5
Summary: SEO and Custom tools for the Django CMS
Home-page: https://github.com/werevolff/django_cms_seotools
Author: Nikolay <Werevolff> Dolganov
Author-email: sirnikolasd@yandex.ru
License: UNKNOWN
Platform: UNKNOWN
